rtctools_diagnostics/__init__.py
rtctools_diagnostics/_version.py
rtctools_diagnostics/export_results.py
rtctools_diagnostics/get_linear_problem.py
rtctools_diagnostics/utils/__init__.py
rtctools_diagnostics/utils/casadi_to_lp.py
rtc_tools_diagnostics-0.2.4.dist-info/COPYING.LESSER
rtc_tools_diagnostics-0.2.4.dist-info/METADATA
rtc_tools_diagnostics-0.2.4.dist-info/WHEEL
rtc_tools_diagnostics-0.2.4.dist-info/top_level.txt
rtc_tools_diagnostics-0.2.4.dist-info/RECORD
